{"nodes":[{"id":"dashboard_actions","label":"actions.ts","file_type":"code","source_file":"/root/Skin-IQ/frontend/src/app/[locale]/(admin)/admin/dashboard/actions.ts","source_location":"L1"},{"id":"dashboard_actions_getdashboardstats","label":"getDashboardStats()","file_type":"code","source_file":"/root/Skin-IQ/frontend/src/app/[locale]/(admin)/admin/dashboard/actions.ts","source_location":"L5"},{"id":"dashboard_actions_getdebtreportdata","label":"getDebtReportData()","file_type":"code","source_file":"/root/Skin-IQ/frontend/src/app/[locale]/(admin)/admin/dashboard/actions.ts","source_location":"L146"}],"edges":[{"source":"dashboard_actions","target":"root_skin_iq_frontend_src_utils_supabase_server_ts","relation":"imports_from","confidence":"EXTRACTED","source_file":"/root/Skin-IQ/frontend/src/app/[locale]/(admin)/admin/dashboard/actions.ts","source_location":"L3","weight":1},{"source":"dashboard_actions","target":"supabase_server_createclient","relation":"imports","confidence":"EXTRACTED","source_file":"/root/Skin-IQ/frontend/src/app/[locale]/(admin)/admin/dashboard/actions.ts","source_location":"L3","weight":1},{"source":"dashboard_actions","target":"dashboard_actions_getdashboardstats","relation":"contains","confidence":"EXTRACTED","source_file":"/root/Skin-IQ/frontend/src/app/[locale]/(admin)/admin/dashboard/actions.ts","source_location":"L5","weight":1},{"source":"dashboard_actions","target":"dashboard_actions_getdebtreportdata","relation":"contains","confidence":"EXTRACTED","source_file":"/root/Skin-IQ/frontend/src/app/[locale]/(admin)/admin/dashboard/actions.ts","source_location":"L146","weight":1}]}